{
  "indexes": [
    {
      "collectionGroup": "alerts",
      "queryScope": "COLLECTION",
      "fields": [
        { "fieldPath": "active", "order": "ASCENDING" },
        { "fieldPath": "endDate", "order": "ASCENDING" }
      ]
    },
    {
      "collectionGroup": "pages",
      "queryScope": "COLLECTION",
      "fields": [
        { "fieldPath": "status", "order": "ASCENDING" },
        { "fieldPath": "menuOrder", "order": "ASCENDING" }
      ]
    },
    {
      "collectionGroup": "pages",
      "queryScope": "COLLECTION",
      "fields": [
        { "fieldPath": "slug", "order": "ASCENDING" },
        { "fieldPath": "status", "order": "ASCENDING" }
      ]
    }
  ],
  "fieldOverrides": []
}
